profanity_check/__init__.py
profanity_check/profanity_check.py
profanity_check/data/model.joblib
profanity_check/data/tagalog_model.joblib
profanity_check/data/tagalog_vectorizer.joblib
profanity_check/data/vectorizer.joblib
tests/__init__.py
tests/test_profanity_check.py
bleepy_profanity_check-0.1.9.dist-info/LICENSE
bleepy_profanity_check-0.1.9.dist-info/METADATA
bleepy_profanity_check-0.1.9.dist-info/WHEEL
bleepy_profanity_check-0.1.9.dist-info/top_level.txt
bleepy_profanity_check-0.1.9.dist-info/RECORD
