Metadata-Version: 2.1
Name: bleepy-profanity-check
Version: 0.1.9
Summary: A fast, robust library to check for offensive language in strings. This version of "profanity-check" is used by Bleepy. 
Home-page: https://github.com/reyniel26/bleepy-profanity-check
Author: Victor Zhou (original author), Menelaos Kotoglou, Dimitrios Mistriotis, Reyniel Mark T. Escamillas
Author-email: "Victor Zhou (original author), Menelaos Kotoglou, Dimitrios Mistriotis, and Reyniel Mark Escamillas" <rtescamillas@ccc.edu.ph>
Project-URL: Homepage, https://github.com/reyniel26/bleepy-profanity-check
Project-URL: Bug Tracker, https://github.com/reyniel26/bleepy-profanity-check/issues
Classifier: Development Status :: 5 - Production/Stable
Classifier: Natural Language :: English
Classifier: Programming Language :: Python :: 3
Classifier: License :: OSI Approved :: MIT License
Classifier: Operating System :: OS Independent
Requires-Python: >=3.7
License-File: LICENSE
Requires-Dist: scikit-learn (==1.1.3)
Requires-Dist: joblib (>=1.2.0)
Provides-Extra: tests
Requires-Dist: pytest (>=7.2.0) ; extra == 'tests'
Requires-Dist: pylint (>=2.15.6) ; extra == 'tests'
Requires-Dist: flake8 (>=5.0.4) ; extra == 'tests'
